{"id":97,"source":"Quranic Arabic Corpus morphology (corpus.quran.com) via mustafa0x/quran-morphology","sourceUrl":"http://corpus.quran.com","verses":[{"verseNumber":1,"words":[{"position":1,"segments":"إِنَّآ","irab":"حرف جر — حرف نصب — الصيغة: إِنّ | اسم — متكلم، جمع"},{"position":2,"segments":"أَنزَلْنَٰهُ","irab":"فعل — ماض — باب الفعل: أَفْعَلَ — الجذر: نزل — الصيغة: أَنزَلَ — متكلم، جمع | اسم — متكلم، جمع | اسم — غائب، مذكر، مفرد"},{"position":3,"segments":"فِى","irab":"حرف جر — حرف جر — الصيغة: فِي"},{"position":4,"segments":"لَيْلَةِ","irab":"اسم — الجذر: ليل — الصيغة: لَيْلَة — مجرور"},{"position":5,"segments":"ٱلْقَدْرِ","irab":"حرف جر — ال — الصيغة: ال | اسم — الجذر: قدر — الصيغة: قَدْر — مجرور"}]},{"verseNumber":2,"words":[{"position":1,"segments":"وَمَآ","irab":"حرف جر — حرف عطف — الصيغة: و | اسم — الصيغة: ما"},{"position":2,"segments":"أَدْرَىٰكَ","irab":"فعل — ماض — باب الفعل: أَفْعَلَ — الجذر: دري — الصيغة: أَدْرَى — غائب، مذكر، مفرد | اسم — مخاطب، مذكر، مفرد"},{"position":3,"segments":"مَا","irab":"اسم — الصيغة: ما"},{"position":4,"segments":"لَيْلَةُ","irab":"اسم — الجذر: ليل — الصيغة: لَيْلَة — مرفوع"},{"position":5,"segments":"ٱلْقَدْرِ","irab":"حرف جر — ال — الصيغة: ال | اسم — الجذر: قدر — الصيغة: قَدْر — مجرور"}]},{"verseNumber":3,"words":[{"position":1,"segments":"لَيْلَةُ","irab":"اسم — الجذر: ليل — الصيغة: لَيْلَة — مرفوع"},{"position":2,"segments":"ٱلْقَدْرِ","irab":"حرف جر — ال — الصيغة: ال | اسم — الجذر: قدر — الصيغة: قَدْر — مجرور"},{"position":3,"segments":"خَيْرٌ","irab":"اسم — الجذر: خير — الصيغة: خَيْر — مذكر، مفرد — نكرة — مرفوع"},{"position":4,"segments":"مِّنْ","irab":"حرف جر — حرف جر — الصيغة: مِن"},{"position":5,"segments":"أَلْفِ","irab":"اسم — الجذر: ألف — الصيغة: أَلْف — مجرور"},{"position":6,"segments":"شَهْرٍ","irab":"اسم — الجذر: شهر — الصيغة: شَهْر — نكرة — مجرور"}]},{"verseNumber":4,"words":[{"position":1,"segments":"تَنَزَّلُ","irab":"فعل — مضارع — باب الفعل: تَفَعَّلَ — الجذر: نزل — الصيغة: تَنَزَّلَتْ — غائب، مؤنث، مفرد — الإعراب: مرفوع"},{"position":2,"segments":"ٱلْمَلَٰٓئِكَةُ","irab":"حرف جر — ال — الصيغة: ال | اسم — الجذر: ملك — الصيغة: مَلَك — مذكر، جمع — مرفوع"},{"position":3,"segments":"وَٱلرُّوحُ","irab":"حرف جر — حرف عطف — الصيغة: و | حرف جر — ال — الصيغة: ال | اسم — الجذر: روح — الصيغة: رُوح — مرفوع"},{"position":4,"segments":"فِيهَا","irab":"حرف جر — حرف جر — الصيغة: فِي | اسم — غائب، مؤنث، مفرد"},{"position":5,"segments":"بِإِذْنِ","irab":"حرف جر — حرف جر — الصيغة: ب | اسم — الجذر: أذن — الصيغة: إِذْن — مجرور"},{"position":6,"segments":"رَبِّهِم","irab":"اسم — الجذر: ربب — الصيغة: رَبّ — مجرور | اسم — غائب، مذكر، جمع"},{"position":7,"segments":"مِّن","irab":"حرف جر — حرف جر — الصيغة: مِن"},{"position":8,"segments":"كُلِّ","irab":"اسم — الجذر: كلل — الصيغة: كُلّ — مجرور"},{"position":9,"segments":"أَمْرٍ","irab":"اسم — الجذر: أمر — الصيغة: أَمْر — نكرة — مجرور"}]},{"verseNumber":5,"words":[{"position":1,"segments":"سَلَٰمٌ","irab":"اسم — الجذر: سلم — الصيغة: سَلام — نكرة — مرفوع"},{"position":2,"segments":"هِىَ","irab":"اسم — غائب، مؤنث، مفرد"},{"position":3,"segments":"حَتَّىٰ","irab":"حرف جر — حرف جر — الصيغة: حَتَّى"},{"position":4,"segments":"مَطْلَعِ","irab":"اسم — الجذر: طلع — الصيغة: مَطْلَع — مجرور"},{"position":5,"segments":"ٱلْفَجْرِ","irab":"حرف جر — ال — الصيغة: ال | اسم — الجذر: فجر — الصيغة: فَجْر — مجرور"}]}]}